{
  "owner": "LE GONIDEC",
  "snapshotDate": "2026-02-28",

  "institutions": {
    "boursobank": {
      "id": "boursobank",
      "name": "BoursoBank",
      "type": "BROKER",
      "country": "FR",
      "website": "https://www.boursobank.com"
    },
    "lcl": {
      "id": "lcl",
      "name": "LCL",
      "type": "INSURANCE",
      "country": "FR",
      "website": "https://www.lcl.fr"
    },
    "binance": {
      "id": "binance",
      "name": "Binance",
      "type": "CRYPTO_EXCHANGE",
      "country": "KY",
      "website": "https://www.binance.com"
    },
    "natixis": {
      "id": "natixis",
      "name": "Natixis Intérépargnement",
      "type": "EMPLOYEE_SAVINGS",
      "country": "FR",
      "website": "https://www.natixis-interepargne.com"
    },
    "amundi": {
      "id": "amundi",
      "name": "Amundi",
      "type": "EMPLOYEE_SAVINGS",
      "country": "FR",
      "website": "https://www.amundi-ee.com"
    }
  },

  "accounts": [

    {
      "id": "boursobank-pea",
      "institutionId": "boursobank",
      "type": "PEA",
      "name": "PEA LE GONIDEC",
      "accountNumber": "00088590783",
      "managementMode": "FREE",
      "snapshotDate": "2026-02-28",
      "totalValue": 6348.80,
      "cashBalance": 8.51,
      "securitiesValue": 6340.29,
      "unrealizedPnL": -24.67,
      "unrealizedPnLPercent": -0.39,
      "perf2026": 0.23,
      "perfLastMonth": 2.03,
      "perfYesterday": -0.61,
      "contributionCeiling": 150000,
      "totalContributed": 6086.57,
      "openedAt": "2023-08-21",
      "holdings": [
        {
          "id": "pea-hermes",
          "name": "Hermès International",
          "isin": "FR0000052292",
          "assetClass": "EQUITIES",
          "geography": ["FRANCE", "EUROPE"],
          "quantity": 1,
          "currency": "EUR",
          "unitCostPrice": 2394.36,
          "currentPrice": 2049.00,
          "currentValue": 2049.00,
          "unrealizedPnL": -345.36,
          "unrealizedPnLPercent": -14.42,
          "lastValuationDate": "2026-02-28"
        },
        {
          "id": "pea-amundi-sp500",
          "name": "Amundi PEA S&P 500 UCITS ETF ACC",
          "isin": "FR0011871128",
          "assetClass": "EQUITIES",
          "geography": ["US"],
          "quantity": 18,
          "currency": "EUR",
          "unitCostPrice": 48.70,
          "currentPrice": 50.93,
          "currentValue": 916.72,
          "unrealizedPnL": 40.11,
          "unrealizedPnLPercent": 4.58,
          "lastValuationDate": "2026-02-28"
        },
        {
          "id": "pea-amundi-emerging-asia",
          "name": "Amundi PEA MSCI Emerging Asia Screened UCITS ETF",
          "isin": "FR0013412012",
          "assetClass": "EQUITIES",
          "geography": ["EMERGING_ASIA"],
          "quantity": 21,
          "currency": "EUR",
          "unitCostPrice": 32.12,
          "currentPrice": 34.48,
          "currentValue": 724.16,
          "unrealizedPnL": 49.54,
          "unrealizedPnLPercent": 7.34,
          "lastValuationDate": "2026-02-28"
        },
        {
          "id": "pea-amundi-nasdaq",
          "name": "Amundi PEA NASDAQ-100 UCITS ETF ACC",
          "isin": "FR0011871110",
          "assetClass": "EQUITIES",
          "geography": ["US"],
          "quantity": 7,
          "currency": "EUR",
          "unitCostPrice": 82.95,
          "currentPrice": 84.69,
          "currentValue": 592.83,
          "unrealizedPnL": 12.16,
          "unrealizedPnLPercent": 2.09,
          "lastValuationDate": "2026-02-28"
        },
        {
          "id": "pea-lvmh",
          "name": "LVMH",
          "isin": "FR0000121014",
          "assetClass": "EQUITIES",
          "geography": ["FRANCE", "EUROPE"],
          "quantity": 1,
          "currency": "EUR",
          "unitCostPrice": 508.74,
          "currentPrice": 544.10,
          "currentValue": 544.10,
          "unrealizedPnL": 35.36,
          "unrealizedPnLPercent": 6.95,
          "lastValuationDate": "2026-02-28"
        },
        {
          "id": "pea-air-liquide",
          "name": "Air Liquide",
          "isin": "FR0000120073",
          "assetClass": "EQUITIES",
          "geography": ["FRANCE", "EUROPE"],
          "quantity": 2,
          "currency": "EUR",
          "unitCostPrice": 167.62,
          "currentPrice": 178.24,
          "currentValue": 356.48,
          "unrealizedPnL": 21.25,
          "unrealizedPnLPercent": 6.34,
          "lastValuationDate": "2026-02-28"
        },
        {
          "id": "pea-dassault-aviation",
          "name": "Dassault Aviation",
          "isin": "FR0014004L86",
          "assetClass": "EQUITIES",
          "geography": ["FRANCE", "EUROPE"],
          "quantity": 1,
          "currency": "EUR",
          "unitCostPrice": 303.91,
          "currentPrice": 338.60,
          "currentValue": 338.60,
          "unrealizedPnL": 34.69,
          "unrealizedPnLPercent": 11.41,
          "lastValuationDate": "2026-02-28"
        },
        {
          "id": "pea-totalenergies",
          "name": "TotalEnergies",
          "isin": "FR0000120271",
          "assetClass": "EQUITIES",
          "geography": ["FRANCE", "EUROPE"],
          "quantity": 5,
          "currency": "EUR",
          "unitCostPrice": 53.11,
          "currentPrice": 67.28,
          "currentValue": 336.40,
          "unrealizedPnL": 70.84,
          "unrealizedPnLPercent": 26.68,
          "lastValuationDate": "2026-02-28"
        },
        {
          "id": "pea-amundi-msci-world",
          "name": "Amundi PEA Monde MSCI World UCITS ETF ACC",
          "isin": "FR001400U5Q4",
          "assetClass": "EQUITIES",
          "geography": ["US", "EUROPE", "JAPAN"],
          "quantity": 54,
          "currency": "EUR",
          "unitCostPrice": 5.27,
          "currentPrice": 5.51,
          "currentValue": 297.76,
          "unrealizedPnL": 13.40,
          "unrealizedPnLPercent": 4.71,
          "lastValuationDate": "2026-02-28"
        },
        {
          "id": "pea-airbus",
          "name": "Airbus",
          "isin": "NL0000235190",
          "assetClass": "EQUITIES",
          "geography": ["EUROPE"],
          "quantity": 1,
          "currency": "EUR",
          "unitCostPrice": 140.90,
          "currentPrice": 184.24,
          "currentValue": 184.24,
          "unrealizedPnL": 43.34,
          "unrealizedPnLPercent": 30.76,
          "lastValuationDate": "2026-02-28"
        }
      ]
    },

    {
      "id": "boursobank-cto",
      "institutionId": "boursobank",
      "type": "CTO",
      "name": "CTO LE GONIDEC",
      "accountNumber": "00080077349",
      "managementMode": "FREE",
      "snapshotDate": "2026-02-28",
      "totalValue": 112.25,
      "cashBalance": 0.00,
      "securitiesValue": 112.25,
      "unrealizedPnL": -104.33,
      "unrealizedPnLPercent": -48.17,
      "perf2026": -11.02,
      "perfLastMonth": -4.34,
      "perfYesterday": 19.07,
      "openedAt": "2025-10-24",
      "holdings": [
        {
          "id": "cto-ionq",
          "name": "IonQ",
          "isin": "US46222L1089",
          "ticker": "IONQ",
          "assetClass": "EQUITIES",
          "geography": ["US"],
          "quantity": 3,
          "currency": "EUR",
          "unitCostPrice": 57.44,
          "currentPrice": 32.50,
          "currentValue": 97.50,
          "unrealizedPnL": -74.81,
          "unrealizedPnLPercent": -43.42,
          "lastValuationDate": "2026-02-28",
          "notes": "Informatique quantique — position spéculative"
        },
        {
          "id": "cto-rigetti",
          "name": "Rigetti Computing",
          "isin": "US76655K1034",
          "ticker": "RGTI",
          "assetClass": "EQUITIES",
          "geography": ["US"],
          "quantity": 1,
          "currency": "EUR",
          "unitCostPrice": 44.28,
          "currentPrice": 14.76,
          "currentValue": 14.76,
          "unrealizedPnL": -29.52,
          "unrealizedPnLPercent": -66.67,
          "lastValuationDate": "2026-02-28",
          "notes": "Informatique quantique — position spéculative"
        }
      ]
    },

    {
      "id": "boursobank-livret-a",
      "institutionId": "boursobank",
      "type": "LIVRET_A",
      "name": "Livret A BoursoBank",
      "managementMode": "FREE",
      "snapshotDate": "2026-02-28",
      "totalValue": 707.00,
      "cashBalance": 707.00,
      "securitiesValue": 0,
      "holdings": [
        {
          "id": "livret-a-cash",
          "name": "Livret A",
          "assetClass": "CASH",
          "geography": ["FRANCE"],
          "quantity": 707.00,
          "currency": "EUR",
          "currentValue": 707.00,
          "lastValuationDate": "2026-02-28",
          "notes": "Taux réglementé 3% — garanti"
        }
      ]
    },

    {
      "id": "lcl-av",
      "institutionId": "lcl",
      "type": "AV",
      "name": "LCL Vie",
      "accountNumber": "130168701C",
      "managementMode": "FREE",
      "snapshotDate": "2026-02-27",
      "totalValue": 34218.64,
      "cashBalance": 0,
      "securitiesValue": 34218.64,
      "unrealizedPnL": 1775.86,
      "unrealizedPnLPercent": 5.48,
      "holdings": [
        {
          "id": "av-lcl-fonds-euros",
          "name": "Support Euro LCL Vie",
          "assetClass": "BONDS",
          "geography": ["UNKNOWN"],
          "quantity": 1,
          "currency": "EUR",
          "currentValue": 23606.42,
          "unrealizedPnL": 936.86,
          "unrealizedPnLPercent": 4.13,
          "lastValuationDate": "2026-02-27",
          "notes": "Fonds euros garanti en capital"
        },
        {
          "id": "av-lcl-equilibre-etf",
          "name": "LCL Équilibre ETF Select",
          "isin": "FR0010833715",
          "assetClass": "MIXED",
          "geography": ["US", "EUROPE"],
          "quantity": 54.79818,
          "currency": "EUR",
          "currentValue": 10572.76,
          "unrealizedPnL": 839.00,
          "unrealizedPnLPercent": 8.62,
          "lastValuationDate": "2026-02-23"
        }
      ],
      "geographyBreakdown": [
        { "zone": "US", "value": 4305.38, "percent": 13.25 },
        { "zone": "EUROPE", "value": 4247.01, "percent": 13.07 },
        { "zone": "EMERGING_ASIA", "value": 325.80, "percent": 1.00 },
        { "zone": "UNKNOWN", "value": 23606.42, "percent": 72.67 }
      ]
    },

    {
      "id": "natixis-perco",
      "institutionId": "natixis",
      "type": "PERCO",
      "name": "Plan Épargne Retraite Collectif",
      "accountNumber": "8764-PERCO",
      "managementMode": "FREE",
      "snapshotDate": "2026-02-27",
      "totalValue": 1335.48,
      "cashBalance": 0,
      "securitiesValue": 1335.48,
      "unrealizedPnL": 32.49,
      "unrealizedPnLPercent": 2.49,
      "holdings": [
        {
          "id": "perco-natixis-expertise-esq-eq-1",
          "name": "Expertise ESG Équilibre I",
          "assetClass": "MIXED",
          "geography": ["EUROPE", "GLOBAL"],
          "quantity": 2.59,
          "currency": "EUR",
          "currentValue": 279.60,
          "unrealizedPnL": 8.69,
          "unrealizedPnLPercent": 3.21,
          "perf1y": 3.21,
          "riskLevel": 3,
          "lastValuationDate": "2026-02-24"
        },
        {
          "id": "perco-natixis-avenir-actions-1",
          "name": "Avenir Actions Europe I",
          "assetClass": "EQUITIES",
          "geography": ["EUROPE"],
          "quantity": 4.07,
          "currency": "EUR",
          "currentValue": 191.73,
          "unrealizedPnL": 11.12,
          "unrealizedPnLPercent": 6.16,
          "perf1y": 6.16,
          "riskLevel": 5,
          "lastValuationDate": "2026-02-25"
        },
        {
          "id": "perco-natixis-dnca-serenite-1",
          "name": "Selection DNCA Sérénité Plus I",
          "assetClass": "MIXED",
          "geography": ["EUROPE"],
          "quantity": 35.40,
          "currency": "EUR",
          "currentValue": 181.97,
          "unrealizedPnL": 1.37,
          "unrealizedPnLPercent": 0.76,
          "perf1y": 0.76,
          "riskLevel": 3,
          "lastValuationDate": "2026-02-25"
        },
        {
          "id": "perco-natixis-mirova-intl-1",
          "name": "Selection Mirova Actions Internationales I",
          "assetClass": "EQUITIES",
          "geography": ["GLOBAL"],
          "quantity": 4.84,
          "currency": "EUR",
          "currentValue": 181.59,
          "unrealizedPnL": 0.99,
          "unrealizedPnLPercent": 0.55,
          "perf1y": 0.55,
          "riskLevel": 5,
          "lastValuationDate": "2026-02-25"
        },
        {
          "id": "perco-natixis-expertise-esq-eq-2",
          "name": "Expertise ESG Équilibre I (tranche 2)",
          "assetClass": "MIXED",
          "geography": ["EUROPE", "GLOBAL"],
          "quantity": 1.15,
          "currency": "EUR",
          "currentValue": 123.84,
          "unrealizedPnL": 3.85,
          "unrealizedPnLPercent": 3.21,
          "riskLevel": 3,
          "lastValuationDate": "2026-02-24"
        },
        {
          "id": "perco-natixis-monetaire-1",
          "name": "Épargne ISR Monétaire I",
          "assetClass": "MONEY_MARKET",
          "geography": ["EUROPE"],
          "quantity": 4.67,
          "currency": "EUR",
          "currentValue": 90.64,
          "unrealizedPnL": 0.34,
          "unrealizedPnLPercent": 0.38,
          "riskLevel": 1,
          "lastValuationDate": "2026-02-25"
        },
        {
          "id": "perco-natixis-avenir-actions-2",
          "name": "Avenir Actions Europe I (tranche 2)",
          "assetClass": "EQUITIES",
          "geography": ["EUROPE"],
          "quantity": 1.80,
          "currency": "EUR",
          "currentValue": 84.92,
          "unrealizedPnL": 4.93,
          "unrealizedPnLPercent": 6.16,
          "riskLevel": 5,
          "lastValuationDate": "2026-02-25"
        },
        {
          "id": "perco-natixis-dnca-serenite-2",
          "name": "Selection DNCA Sérénité Plus I (tranche 2)",
          "assetClass": "MIXED",
          "geography": ["EUROPE"],
          "quantity": 15.68,
          "currency": "EUR",
          "currentValue": 80.61,
          "unrealizedPnL": 0.61,
          "unrealizedPnLPercent": 0.76,
          "riskLevel": 3,
          "lastValuationDate": "2026-02-25"
        },
        {
          "id": "perco-natixis-mirova-intl-2",
          "name": "Selection Mirova Actions Internationales I (tranche 2)",
          "assetClass": "EQUITIES",
          "geography": ["GLOBAL"],
          "quantity": 2.15,
          "currency": "EUR",
          "currentValue": 80.44,
          "unrealizedPnL": 0.44,
          "unrealizedPnLPercent": 0.55,
          "riskLevel": 5,
          "lastValuationDate": "2026-02-25"
        },
        {
          "id": "perco-natixis-monetaire-2",
          "name": "Épargne ISR Monétaire I (tranche 2)",
          "assetClass": "MONEY_MARKET",
          "geography": ["EUROPE"],
          "quantity": 2.07,
          "currency": "EUR",
          "currentValue": 40.15,
          "unrealizedPnL": 0.15,
          "unrealizedPnLPercent": 0.38,
          "riskLevel": 1,
          "lastValuationDate": "2026-02-25"
        }
      ]
    },

    {
      "id": "natixis-pee",
      "institutionId": "natixis",
      "type": "PEE",
      "name": "Plan Épargne Salariale",
      "accountNumber": "8764-PEE",
      "managementMode": "FREE",
      "snapshotDate": "2026-02-27",
      "totalValue": 3193.61,
      "cashBalance": 0,
      "securitiesValue": 3193.61,
      "unrealizedPnL": 102.08,
      "unrealizedPnLPercent": 3.30,
      "holdings": [
        {
          "id": "pee-natixis-mirova-intl-1",
          "name": "Selection Mirova Actions Internationales I",
          "assetClass": "EQUITIES",
          "geography": ["GLOBAL"],
          "quantity": 18.15,
          "currency": "EUR",
          "currentValue": 680.41,
          "unrealizedPnL": 3.69,
          "unrealizedPnLPercent": 0.55,
          "perf1y": 0.55,
          "riskLevel": 5,
          "lastValuationDate": "2026-02-25"
        },
        {
          "id": "pee-natixis-expertise-eq-1",
          "name": "Expertise ESG Équilibre I",
          "assetClass": "MIXED",
          "geography": ["EUROPE", "GLOBAL"],
          "quantity": 5.39,
          "currency": "EUR",
          "currentValue": 581.09,
          "unrealizedPnL": 18.06,
          "unrealizedPnLPercent": 3.21,
          "perf1y": 3.21,
          "riskLevel": 3,
          "lastValuationDate": "2026-02-24"
        },
        {
          "id": "pee-natixis-avenir-europe-1",
          "name": "Avenir Actions Europe I",
          "assetClass": "EQUITIES",
          "geography": ["EUROPE"],
          "quantity": 10.06,
          "currency": "EUR",
          "currentValue": 474.13,
          "unrealizedPnL": 27.51,
          "unrealizedPnLPercent": 6.16,
          "perf1y": 6.16,
          "riskLevel": 5,
          "lastValuationDate": "2026-02-25"
        },
        {
          "id": "pee-natixis-mirova-intl-2",
          "name": "Selection Mirova Actions Internationales I (tranche 2)",
          "assetClass": "EQUITIES",
          "geography": ["GLOBAL"],
          "quantity": 6.71,
          "currency": "EUR",
          "currentValue": 251.37,
          "unrealizedPnL": 1.36,
          "unrealizedPnLPercent": 0.54,
          "riskLevel": 5,
          "lastValuationDate": "2026-02-25"
        },
        {
          "id": "pee-natixis-expertise-dyn",
          "name": "Expertise ESG Dynamique I",
          "assetClass": "EQUITIES",
          "geography": ["EUROPE", "GLOBAL"],
          "quantity": 1.85,
          "currency": "EUR",
          "currentValue": 247.80,
          "unrealizedPnL": 23.13,
          "unrealizedPnLPercent": 10.30,
          "perf1y": 10.30,
          "riskLevel": 4,
          "lastValuationDate": "2026-02-24"
        },
        {
          "id": "pee-natixis-dnca-serenite-1",
          "name": "Selection DNCA Sérénité Plus I",
          "assetClass": "MIXED",
          "geography": ["EUROPE"],
          "quantity": 44.04,
          "currency": "EUR",
          "currentValue": 226.37,
          "unrealizedPnL": 1.70,
          "unrealizedPnLPercent": 0.76,
          "riskLevel": 3,
          "lastValuationDate": "2026-02-25"
        },
        {
          "id": "pee-natixis-expertise-eq-2",
          "name": "Expertise ESG Équilibre I (tranche 2)",
          "assetClass": "MIXED",
          "geography": ["EUROPE", "GLOBAL"],
          "quantity": 1.99,
          "currency": "EUR",
          "currentValue": 214.68,
          "unrealizedPnL": 6.67,
          "unrealizedPnLPercent": 3.21,
          "riskLevel": 3,
          "lastValuationDate": "2026-02-24"
        },
        {
          "id": "pee-natixis-avenir-europe-2",
          "name": "Avenir Actions Europe I (tranche 2)",
          "assetClass": "EQUITIES",
          "geography": ["EUROPE"],
          "quantity": 3.72,
          "currency": "EUR",
          "currentValue": 175.16,
          "unrealizedPnL": 10.16,
          "unrealizedPnLPercent": 6.16,
          "riskLevel": 5,
          "lastValuationDate": "2026-02-25"
        },
        {
          "id": "pee-natixis-monetaire",
          "name": "Épargne ISR Monétaire I",
          "assetClass": "MONEY_MARKET",
          "geography": ["EUROPE"],
          "quantity": 6.30,
          "currency": "EUR",
          "currentValue": 122.27,
          "unrealizedPnL": 0.46,
          "unrealizedPnLPercent": 0.38,
          "riskLevel": 1,
          "lastValuationDate": "2026-02-25"
        },
        {
          "id": "pee-natixis-expertise-dyn-2",
          "name": "Expertise ESG Dynamique I (tranche 2)",
          "assetClass": "EQUITIES",
          "geography": ["EUROPE", "GLOBAL"],
          "quantity": 0.69,
          "currency": "EUR",
          "currentValue": 91.54,
          "unrealizedPnL": 8.54,
          "unrealizedPnLPercent": 10.29,
          "riskLevel": 4,
          "lastValuationDate": "2026-02-24"
        },
        {
          "id": "pee-natixis-dnca-serenite-2",
          "name": "Selection DNCA Sérénité Plus I (tranche 2)",
          "assetClass": "MIXED",
          "geography": ["EUROPE"],
          "quantity": 16.27,
          "currency": "EUR",
          "currentValue": 83.63,
          "unrealizedPnL": 0.63,
          "unrealizedPnLPercent": 0.76,
          "riskLevel": 3,
          "lastValuationDate": "2026-02-25"
        },
        {
          "id": "pee-natixis-monetaire-2",
          "name": "Épargne ISR Monétaire I (tranche 2)",
          "assetClass": "MONEY_MARKET",
          "geography": ["EUROPE"],
          "quantity": 2.33,
          "currency": "EUR",
          "currentValue": 45.17,
          "unrealizedPnL": 0.17,
          "unrealizedPnLPercent": 0.38,
          "riskLevel": 1,
          "lastValuationDate": "2026-02-25"
        }
      ]
    },

    {
      "id": "binance-wallet",
      "institutionId": "binance",
      "type": "CRYPTO",
      "name": "Binance Wallet",
      "managementMode": "FREE",
      "snapshotDate": "2026-02-28",
      "totalValue": 1280.43,
      "cashBalance": 0.05,
      "securitiesValue": 1280.38,
      "holdings": [
        {
          "id": "crypto-btc",
          "name": "Bitcoin",
          "ticker": "BTC",
          "assetClass": "CRYPTO",
          "geography": ["CRYPTO_GLOBAL"],
          "quantity": 0.0121236,
          "currency": "BTC",
          "currentValue": 659.00,
          "lastValuationDate": "2026-02-28"
        },
        {
          "id": "crypto-eth",
          "name": "Ethereum",
          "ticker": "ETH",
          "assetClass": "CRYPTO",
          "geography": ["CRYPTO_GLOBAL"],
          "quantity": 0.274610,
          "currency": "ETH",
          "currentValue": 436.27,
          "lastValuationDate": "2026-02-28"
        },
        {
          "id": "crypto-usdc",
          "name": "USD Coin",
          "ticker": "USDC",
          "assetClass": "CASH",
          "geography": ["CRYPTO_GLOBAL"],
          "quantity": 5.28845,
          "currency": "USDC",
          "currentValue": 84.49,
          "lastValuationDate": "2026-02-28",
          "notes": "Stablecoin adossé à l'USD"
        },
        {
          "id": "crypto-sol",
          "name": "Solana",
          "ticker": "SOL",
          "assetClass": "CRYPTO",
          "geography": ["CRYPTO_GLOBAL"],
          "quantity": 1.214184,
          "currency": "SOL",
          "currentValue": 81.56,
          "lastValuationDate": "2026-02-28"
        },
        {
          "id": "crypto-bnb",
          "name": "BNB",
          "ticker": "BNB",
          "assetClass": "CRYPTO",
          "geography": ["CRYPTO_GLOBAL"],
          "quantity": 0.037633,
          "currency": "BNB",
          "currentValue": 19.06,
          "lastValuationDate": "2026-02-28"
        },
        {
          "id": "crypto-eur",
          "name": "EUR (Binance)",
          "assetClass": "CASH",
          "geography": ["EUROPE"],
          "quantity": 0.05,
          "currency": "EUR",
          "currentValue": 0.05,
          "lastValuationDate": "2026-02-28"
        }
      ]
    },

    {
      "id": "amundi-pee-ds",
      "institutionId": "amundi",
      "type": "PEE",
      "name": "Plan Épargne Entreprise — Dassault Systèmes",
      "managementMode": "FREE",
      "snapshotDate": "2026-02-27",
      "totalValue": 8293.26,
      "cashBalance": 0,
      "securitiesValue": 8293.26,
      "fiscalPnL": 677.93,
      "estimatedNetValue": 8167.17,
      "holdings": [
        {
          "id": "pee-amundi-ds-actions-monde",
          "name": "Dassault Systèmes Actions Monde",
          "assetClass": "EQUITIES",
          "geography": ["GLOBAL"],
          "quantity": 205.8939,
          "currency": "EUR",
          "currentPrice": 14.71,
          "currentValue": 3028.70,
          "fiscalPnL": 458.50,
          "perf1y": 10.77,
          "riskLevel": 4,
          "lastValuationDate": "2026-02-26"
        },
        {
          "id": "pee-amundi-ds-isr-dynamique",
          "name": "Dassault Systèmes ISR Dynamique",
          "assetClass": "MIXED",
          "geography": ["GLOBAL"],
          "quantity": 49.3711,
          "currency": "EUR",
          "currentPrice": 34.37598,
          "currentValue": 1697.18,
          "fiscalPnL": 81.73,
          "perf1y": 0.76,
          "perf5yAnnualized": 4.07,
          "perf5yCumulated": 22.07,
          "riskLevel": 3,
          "lastValuationDate": "2026-02-26"
        },
        {
          "id": "pee-amundi-ds-isr-equilibre",
          "name": "Dassault Systèmes ISR Équilibre",
          "assetClass": "MIXED",
          "geography": ["GLOBAL"],
          "quantity": 148.3731,
          "currency": "EUR",
          "currentPrice": 10.64677,
          "currentValue": 1579.69,
          "fiscalPnL": 78.66,
          "perf1y": 1.49,
          "riskLevel": 3,
          "lastValuationDate": "2026-02-26"
        },
        {
          "id": "pee-amundi-ds-isr-modere-solidaire",
          "name": "Dassault Systèmes ISR Modéré Solidaire",
          "assetClass": "MIXED",
          "geography": ["GLOBAL"],
          "quantity": 99.2412,
          "currency": "EUR",
          "currentPrice": 10.083,
          "currentValue": 1000.65,
          "fiscalPnL": 53.25,
          "perf1y": 4.20,
          "riskLevel": 2,
          "lastValuationDate": "2026-02-26"
        },
        {
          "id": "pee-amundi-together-2025",
          "name": "Together Multiple 2025 France",
          "assetClass": "MIXED",
          "geography": ["FRANCE"],
          "quantity": 26.0777,
          "currency": "EUR",
          "currentPrice": 28.20,
          "currentValue": 735.39,
          "fiscalPnL": 0,
          "riskLevel": 3,
          "lastValuationDate": "2026-01-30"
        },
        {
          "id": "pee-amundi-label-monetaire",
          "name": "Amundi Label Monétaire ESR — F",
          "assetClass": "MONEY_MARKET",
          "geography": ["EUROPE"],
          "quantity": 0.1934,
          "currency": "EUR",
          "currentPrice": 1301.1801,
          "currentValue": 251.65,
          "fiscalPnL": 5.79,
          "perf1y": 2.03,
          "perf5yAnnualized": 1.73,
          "perf5yCumulated": 8.96,
          "riskLevel": 1,
          "lastValuationDate": "2026-02-27"
        }
      ]
    },

    {
      "id": "amundi-percol-ds",
      "institutionId": "amundi",
      "type": "PERCOL",
      "name": "PER Collectif — Dassault Systèmes",
      "managementMode": "PILOTED",
      "managementProfile": "Dynamique",
      "snapshotDate": "2026-02-27",
      "totalValue": 5041.13,
      "cashBalance": 0,
      "securitiesValue": 5041.13,
      "fiscalPnL": 472.93,
      "holdings": [
        {
          "id": "percol-amundi-convictions-esr",
          "name": "Amundi Convictions ESR — F",
          "assetClass": "EQUITIES",
          "geography": ["GLOBAL"],
          "quantity": 23.3873,
          "currency": "EUR",
          "currentPrice": 215.55,
          "currentValue": 5041.13,
          "fiscalPnL": 472.93,
          "perf1y": 7.72,
          "perf5yAnnualized": 5.97,
          "perf5yCumulated": 33.64,
          "riskLevel": 4,
          "lastValuationDate": "2026-02-26"
        }
      ]
    }

  ]
}
